treelog/__init__.py
treelog/_forward.py
treelog/_html.py
treelog/_io.py
treelog/_silent.py
treelog/_text.py
treelog/iter.py
treelog/proto.py
treelog/py.typed
treelog-1.0.dist-info/LICENSE
treelog-1.0.dist-info/METADATA
treelog-1.0.dist-info/WHEEL
treelog-1.0.dist-info/top_level.txt
treelog-1.0.dist-info/RECORD
